{
    "error": "false",
    "response": {
        "solutions": {
            "re_features_v3": {
                "detections": []
            },
            "re_roomtype_global_v2": {
                "predictions": [
                    {
                        "label": "details",
                        "confidence": 0.5140388607978821
                    },
                    {
                        "label": "exercise_room",
                        "confidence": 0.38423219323158264
                    },
                    {
                        "label": "game_room",
                        "confidence": 0.019481422379612923
                    },
                    {
                        "label": "documents",
                        "confidence": 0.008064397610723972
                    },
                    {
                        "label": "reception",
                        "confidence": 0.007768077775835991
                    }
                ],
                "top_prediction": {
                    "label": "details",
                    "confidence": 0.5140388607978821
                }
            },
            "re_condition": {
                "score": null
            },
            "re_appliances_v2": {
                "detections": []
            }
        }
    },
    "time": "2022-04-30T20:48:53.261973",
    "correlation_id": "4fde579c-7b26-4da2-bd02-34bcf645e524",
    "version": "2"
}